LICENSE
setup.py
chatapi_translate/__init__.py
chatapi_translate/api.py
chatapi_translate/utils.py
chatapi_translate.egg-info/PKG-INFO
chatapi_translate.egg-info/SOURCES.txt
chatapi_translate.egg-info/dependency_links.txt
chatapi_translate.egg-info/entry_points.txt
chatapi_translate.egg-info/requires.txt
chatapi_translate.egg-info/top_level.txt
chatapi_translate/translator/__init__.py
chatapi_translate/translator/ali.py
chatapi_translate/translator/baidu.py
chatapi_translate/translator/caiyun.py
chatapi_translate/translator/chatgpt.py
chatapi_translate/translator/deepl.py
chatapi_translate/translator/google.py
chatapi_translate/translator/tencent.py
chatapi_translate/translator/utils.py
chatapi_translate/translator/volcengine.py