Metadata-Version: 2.1
Name: chatapi-translate
Version: 0.7
Summary: ChatGPT OpenAI API 流式反向代理，自动翻译中文到英文对话，实现用英文进行高质量的对话
Home-page: https://github.com/aitsc/chatapi-translate
Author: aitsc
License: MIT
Keywords: tools
Classifier: Intended Audience :: Developers
Classifier: License :: OSI Approved :: MIT License
Classifier: Programming Language :: Python :: 3 :: Only
Classifier: Topic :: Software Development :: Libraries
Requires-Python: >=3.7
License-File: LICENSE
